MANIFEST.in
README.md
requirements.txt
setup.py
nextcode_platform_kit.egg-info/PKG-INFO
nextcode_platform_kit.egg-info/SOURCES.txt
nextcode_platform_kit.egg-info/dependency_links.txt
nextcode_platform_kit.egg-info/not-zip-safe
nextcode_platform_kit.egg-info/requires.txt
nextcode_platform_kit.egg-info/top_level.txt
platkit/VERSION
platkit/__init__.py
platkit/auth.py
platkit/cli.py
platkit/config.py
platkit/csautils.py
platkit/exceptions.py
platkit/flasksetup.py
platkit/librarypatches.py
platkit/logsetup.py
platkit/prometheus.py
platkit/testcase.py
platkit/utils.py
platkit/endpoints/__init__.py
platkit/endpoints/auth.py
platkit/middleware/__init__.py
platkit/middleware/logstash_formatter.py
platkit/middleware/reverse_proxied.py
platkit/models/__init__.py
platkit/models/responses.py